{"cameraMode":{"drawMode":0,"name":"Shaded","section":"Shading Mode"},"sceneLighting":true,"audioPlay":false,"sceneViewState":{"m_AlwaysRefresh":false,"showFog":true,"showSkybox":true,"showFlares":true,"showImageEffects":true,"showParticleSystems":true,"showVisualEffectGraphs":true,"m_FxEnabled":true},"in2DMode":false,"pivot":{"x":-7.194488525390625,"y":-18.829334259033204,"z":1.1760457754135132},"rotation":{"x":0.5265618562698364,"y":-0.10951103270053864,"z":0.06862707436084748,"w":0.8402562141418457},"size":3.3838868141174318,"orthographic":false}